profiles_rudderstack/__init__.py
profiles_rudderstack/go_client.py
profiles_rudderstack/logger.py
profiles_rudderstack/material.py
profiles_rudderstack/model.py
profiles_rudderstack/project.py
profiles_rudderstack/reader.py
profiles_rudderstack/recipe.py
profiles_rudderstack/schema.py
profiles_rudderstack/server.py
profiles_rudderstack/service.py
profiles_rudderstack/utils.py
profiles_rudderstack/wht_context.py
profiles_rudderstack/client/__init__.py
profiles_rudderstack/client/client_base.py
profiles_rudderstack/client/snowpark.py
profiles_rudderstack/client/warehouse.py
profiles_rudderstack/tunnel/__init__.py
profiles_rudderstack/tunnel/tunnel_pb2.py
profiles_rudderstack/tunnel/tunnel_pb2.pyi
profiles_rudderstack/tunnel/tunnel_pb2_grpc.py
profiles_rudderstack/wh/__init__.py
profiles_rudderstack/wh/bigquery_connector.py
profiles_rudderstack/wh/connector_base.py
profiles_rudderstack/wh/databricks_connector.py
profiles_rudderstack/wh/pg_connector.py
profiles_rudderstack/wh/redshift_pb_connector.py
profiles_rudderstack/wh/snowflake_connector.py
profiles_rudderstack-0.24.0.dist-info/METADATA
profiles_rudderstack-0.24.0.dist-info/WHEEL
profiles_rudderstack-0.24.0.dist-info/top_level.txt
profiles_rudderstack-0.24.0.dist-info/RECORD
