Metadata-Version: 2.4
Name: profiles_rudderstack
Version: 0.24.0
Summary: A warehouse-native semantic modeling layer that creates unified customer profiles in your data warehouse
Home-page: https://www.rudderstack.com/
Author: RudderStack
Author-email: profiles@rudderstack.com
Maintainer: RudderStack
Project-URL: Documentation, https://www.rudderstack.com/docs/profiles/overview/
Keywords: rudderstack,profiles,semantic modeling,identity stitching,data modeling,warehouse transformations,transformation,data engineering,c360
Classifier: Development Status :: 5 - Production/Stable
Classifier: Programming Language :: Python :: 3
Classifier: Intended Audience :: Developers
Classifier: License :: OSI Approved :: MIT License
Classifier: Operating System :: MacOS :: MacOS X
Classifier: Operating System :: POSIX :: Linux
Classifier: Operating System :: Microsoft :: Windows
Requires-Python: >=3.8
Requires-Dist: grpcio>=1.60.0
Requires-Dist: grpcio-status<=1.71.0
Requires-Dist: grpc_interceptor>=0.15.4
Requires-Dist: protobuf>=6.31.0
Requires-Dist: pandas<2.2.0,>=1.3.0
Requires-Dist: sqlalchemy-redshift>=0.8.14
Requires-Dist: snowflake-sqlalchemy>=1.5.1
Requires-Dist: pandas-redshift>=2.0.5
Requires-Dist: snowflake-connector-python[pandas]>=3.4.0
Requires-Dist: redshift-connector>=2.0.918
Requires-Dist: sqlalchemy-databricks>=0.2.0
Requires-Dist: sqlalchemy-bigquery>=1.9.0
Requires-Dist: pandas-gbq>=0.22.0
Requires-Dist: google-auth>=2.28.2
Requires-Dist: packaging>=23.2
Requires-Dist: databricks-sdk>=0.62.0
Requires-Dist: profiles_rudderstack_bin==v0.24.0
Provides-Extra: snowpark
Requires-Dist: snowflake-snowpark-python>=1.11.1; extra == "snowpark"
Dynamic: author
Dynamic: author-email
Dynamic: classifier
Dynamic: description
Dynamic: description-content-type
Dynamic: home-page
Dynamic: keywords
Dynamic: maintainer
Dynamic: project-url
Dynamic: provides-extra
Dynamic: requires-dist
Dynamic: requires-python
Dynamic: summary
